words_n_fun/__init__.py
words_n_fun/utils.py
words_n_fun/configs/pipeline_usage_order.json
words_n_fun/nltk_data/corpora/stopwords/french
words_n_fun/preprocessing/__init__.py
words_n_fun/preprocessing/api.py
words_n_fun/preprocessing/basic.py
words_n_fun/preprocessing/lemmatizer.py
words_n_fun/preprocessing/split_sentences.py
words_n_fun/preprocessing/stopwords.py
words_n_fun/preprocessing/synonym_malefemale_replacement.py
words_n_fun/preprocessing/vectorization_tokenization.py
words_n_fun-1.6.1.dist-info/LICENSE
words_n_fun-1.6.1.dist-info/METADATA
words_n_fun-1.6.1.dist-info/WHEEL
words_n_fun-1.6.1.dist-info/top_level.txt
words_n_fun-1.6.1.dist-info/RECORD
