Metadata-Version: 2.1
Name: words-n-fun
Version: 1.6.1
Summary: Semantic library of the Data Services agency
Home-page: https://github.com/OSS-Pole-Emploi/words_n_fun
Author: Agence Data Services PE Nantes
Author-email: contactadsaiframeworks.00619@pole-emploi.fr
License: AGPL-3.0
Platform: windows
Platform: linux
Requires-Python: >=3.8
License-File: LICENSE
Requires-Dist: nltk >=3.4
Requires-Dist: ftfy >=5.8
Requires-Dist: tqdm >=4.40
Requires-Dist: simplejson >=3.17
Requires-Dist: requests >=2.23
Requires-Dist: pandas <1.5,>=1.3 ; python_version < "3.10"
Requires-Dist: numpy <1.24,>=1.19 ; python_version < "3.10"
Requires-Dist: pandas >=1.3 ; python_version >= "3.10"
Requires-Dist: numpy >=1.19 ; python_version >= "3.10"
Provides-Extra: lemmatizer
Requires-Dist: spacy >=3.7.1 ; extra == 'lemmatizer'
Requires-Dist: markupsafe >=2.1.3 ; extra == 'lemmatizer'
Requires-Dist: Cython >=3.0.3 ; extra == 'lemmatizer'
